odoo8_addon_purchase_order_ubl-8.0.1.2.0-nspkg.pth
odoo_addons/purchase_order_ubl/README.rst
odoo_addons/purchase_order_ubl/__init__.py
odoo_addons/purchase_order_ubl/__openerp__.py
odoo_addons/purchase_order_ubl/i18n/purchase_order_ubl.pot
odoo_addons/purchase_order_ubl/models/__init__.py
odoo_addons/purchase_order_ubl/models/purchase.py
odoo_addons/purchase_order_ubl/models/report.py
odoo_addons/purchase_order_ubl/static/description/icon.png
odoo_addons/purchase_order_ubl/tests/__init__.py
odoo_addons/purchase_order_ubl/tests/test_ubl_generate.py
odoo8_addon_purchase_order_ubl-8.0.1.2.0.dist-info/METADATA
odoo8_addon_purchase_order_ubl-8.0.1.2.0.dist-info/WHEEL
odoo8_addon_purchase_order_ubl-8.0.1.2.0.dist-info/namespace_packages.txt
odoo8_addon_purchase_order_ubl-8.0.1.2.0.dist-info/top_level.txt
odoo8_addon_purchase_order_ubl-8.0.1.2.0.dist-info/RECORD
