Metadata-Version: 2.1
Name: odoo8-addon-purchase-order-ubl
Version: 8.0.1.2.0
Summary: Embed UBL XML file inside the PDF purchase order
Home-page: http://www.akretion.com
Author: Akretion,Odoo Community Association (OCA)
Author-email: support@odoo-community.org
License: AGPL-3
Platform: UNKNOWN
Classifier: Programming Language :: Python
Classifier: Framework :: Odoo
Classifier: License :: OSI Approved :: GNU Affero General Public License v3
Requires-Python: ~=2.7
Requires-Dist: odoo8-addon-base-ubl
Requires-Dist: odoo (<9.0a,>=8.0a)
